cro/__init__.py
cro/exchange/__init__.py
cro/exchange/api/__init__.py
cro/exchange/api/base.py
cro/exchange/api/private.py
cro/exchange/api/public.py
py_crypto_com_exchange_client-2020.9.5.dist-info/METADATA
py_crypto_com_exchange_client-2020.9.5.dist-info/WHEEL
py_crypto_com_exchange_client-2020.9.5.dist-info/top_level.txt
py_crypto_com_exchange_client-2020.9.5.dist-info/RECORD
