Metadata-Version: 2.1
Name: py-crypto-com-exchange-client
Version: 2020.9.5
Summary: Python client for Crypto.com exchange APIs
Home-page: UNKNOWN
Author: Nikhil K Madhusudhan (nikhilkmdev)
Author-email: nikhilkmdev@gmail.com
Maintainer: Nikhil K Madhusudhan (nikhilkmdev)
Maintainer-email: nikhilkmdev@gmail.com
License: MIT
Keywords: timeseries,history,python3
Platform: UNKNOWN
Classifier: License :: OSI Approved :: MIT License
Classifier: Programming Language :: Python :: 3
Classifier: Programming Language :: Python :: 3.7
Requires-Dist: py-simple-flow
Requires-Dist: requests (==2.24.0)
Requires-Dist: pandas
Requires-Dist: pyyaml
